[
  {
    "title": "3D Animation",
    "price": 100,
    "path": "/image.png"
  },
  {
    "title": "2D Animation",
    "price": 101,
    "path": "/image.png"
  },
  {
    "title": "Editing / Motion Graphics",
    "price": 102,
    "path": "/image.png"
  },
  {
    "title": "Live Action Production",
    "price": 104,
    "path": "/image.png"
  },
  {
    "title": "Foreign Language",
    "price": 103,
    "path": "/image.png"
  },
  {
    "title": "Characters",
    "price": 105,
    "path": "/image.png"
  },
  {
    "title": "Style hybrid",
    "price": 106,
    "path": "/image.png"
  }
]
